tcga_paired_purification/__init__.py
tcga_paired_purification/purification.py
tcga_paired_purification-0.1.dist-info/LICENSE
tcga_paired_purification-0.1.dist-info/METADATA
tcga_paired_purification-0.1.dist-info/WHEEL
tcga_paired_purification-0.1.dist-info/top_level.txt
tcga_paired_purification-0.1.dist-info/RECORD
