Metadata-Version: 2.1
Name: tcga-paired-purification
Version: 0.1
Summary: Implementation of the TCGA purification protocol
Home-page: https://github.com/jeffliu6068/TCGA_paired_purification
Author: Jeff Liu
Author-email: jeffliu6068@gmail.com
License: LICENSE.txt
Platform: UNKNOWN
Requires-Dist: pandas
Requires-Dist: scipy
Requires-Dist: numpy
Requires-Dist: matplotlib
Requires-Dist: seaborn
Requires-Dist: sklearn
Requires-Dist: tqdm
